CHANGELOG.md
LICENSE
README.md
script_master/__init__.py
script_master/cli.py
script_master/const.py
script_master/files.py
script_master/logger.py
script_master/main.py
script_master/notebook/__init__.py
script_master/notebook/schemas.py
script_master/notebook/service.py
script_master/notebook/tags.py
script_master/resources.py
script_master/service.py
script_master/settings.py
script_master/template-settings.env
script_master/template.py
script_master/utils.py
script_master-0.0.5.dist-info/entry_points.txt
script_master-0.0.5.dist-info/LICENSE
script_master-0.0.5.dist-info/WHEEL
script_master-0.0.5.dist-info/METADATA
script_master-0.0.5.dist-info/RECORD
